setup.py
besti/__init__.py
besti/common.py
besti/product.py
besti/run.py
besti.egg-info/PKG-INFO
besti.egg-info/SOURCES.txt
besti.egg-info/dependency_links.txt
besti.egg-info/top_level.txt
besti/utils/__init__.py
besti/utils/log.py
besti/utils/runner.py
besti/utils/signal.py