Metadata-Version: 2.1
Name: besti
Version: 0.7.5
Summary: 大创项目
Home-page: https://github.com/
Author-email: 2213935054@qq.com
License: UNKNOWN
Platform: UNKNOWN
Classifier: Programming Language :: Python :: 3
Classifier: License :: OSI Approved :: GNU General Public License v3 (GPLv3)
Classifier: Operating System :: OS Independent
